x32dbg/__init__.py
x32dbg-1.0.16.dist-info/LICENSE
x32dbg-1.0.16.dist-info/METADATA
x32dbg-1.0.16.dist-info/WHEEL
x32dbg-1.0.16.dist-info/top_level.txt
x32dbg-1.0.16.dist-info/RECORD
